pastas_munisense/__init__.py
pastas_munisense/dataset.py
pastas_munisense/decorators.py
pastas_munisense/model.py
pastas_munisense/modelstats.py
pastas_munisense/noisemodels.py
pastas_munisense/objective_functions.py
pastas_munisense/rcparams.py
pastas_munisense/recharge.py
pastas_munisense/rfunc.py
pastas_munisense/solver.py
pastas_munisense/stressmodels.py
pastas_munisense/timer.py
pastas_munisense/timeseries.py
pastas_munisense/timeseries_utils.py
pastas_munisense/transform.py
pastas_munisense/utils.py
pastas_munisense/version.py
pastas_munisense/extensions/__init__.py
pastas_munisense/extensions/accessor.py
pastas_munisense/io/__init__.py
pastas_munisense/io/base.py
pastas_munisense/io/pas.py
pastas_munisense/plotting/__init__.py
pastas_munisense/plotting/bokeh.py
pastas_munisense/plotting/modelcompare.py
pastas_munisense/plotting/modelplots.py
pastas_munisense/plotting/plotly.py
pastas_munisense/plotting/plots.py
pastas_munisense/plotting/plotutil.py
pastas_munisense/stats/__init__.py
pastas_munisense/stats/core.py
pastas_munisense/stats/dutch.py
pastas_munisense/stats/metrics.py
pastas_munisense/stats/sgi.py
pastas_munisense/stats/signatures.py
pastas_munisense/stats/tests.py
pastas_munisense/typing/__init__.py
pastas_munisense/typing/types.py
pastas_munisense-1.6.1.dist-info/LICENSE
pastas_munisense-1.6.1.dist-info/METADATA
pastas_munisense-1.6.1.dist-info/WHEEL
pastas_munisense-1.6.1.dist-info/top_level.txt
pastas_munisense-1.6.1.dist-info/RECORD
